CHANGES.txt
CONTRIBUTORS.txt
INSTALL.md
LICENSE.txt
MANIFEST.in
README.md
README.rst
setup.cfg
setup.py
docs/source/Makefile
docs/source/conf.py
docs/source/index.rst
docs/source/make.bat
docs/source/modules.rst
docs/source/pug.bin.rst
docs/source/pug.rst
docs/source/pug.tests.rst
pug/__init__.py
pug/debug.py
pug/decorators.py
pug/noconflict.py
pug/package_info.py
pug/setup_util.py
pug.egg-info/PKG-INFO
pug.egg-info/SOURCES.txt
pug.egg-info/dependency_links.txt
pug.egg-info/requires.txt
pug.egg-info/top_level.txt
pug/bin/install_requirements
pug/bin/push.py
pug/bin/push.sh
pug/bin/register.sh
pug/docs/PDX Python User Group January 2014.md
pug/docs/Pycon_2015_tutorial_application--Practical Natural Language Processing.md
pug/docs/eda.ipynb
pug/docs/presentation.html
pug/docs/slidedeck-pdxpy/Connecting linux and Django to MS and sqlserver.md
pug/docs/slidedeck-pdxpy/base.html
pug/docs/slidedeck-pdxpy/inaugural_cfd.png
pug/docs/slidedeck-pdxpy/index.html
pug/docs/slidedeck-pdxpy/slides.md
pug/docs/slidedeck-pdxpy/figures/200px-6n-graf.svg.png
pug/docs/slidedeck-pdxpy/figures/gpcr_activation.png
pug/docs/slidedeck-pdxpy/js/hammer.js
pug/docs/slidedeck-pdxpy/js/modernizr.custom.45394.js
pug/docs/slidedeck-pdxpy/js/order.js
pug/docs/slidedeck-pdxpy/js/require-1.0.8.min.js
pug/docs/slidedeck-pdxpy/js/slide-controller.js
pug/docs/slidedeck-pdxpy/js/slide-deck.js
pug/docs/slidedeck-pdxpy/js/slides.js
pug/docs/slidedeck-pdxpy/js/polyfills/classList.min.js
pug/docs/slidedeck-pdxpy/js/polyfills/dataset.min.js
pug/docs/slidedeck-pdxpy/js/polyfills/history.min.js
pug/docs/slidedeck-pdxpy/js/prettify/lang-apollo.js
pug/docs/slidedeck-pdxpy/js/prettify/lang-clj.js
pug/docs/slidedeck-pdxpy/js/prettify/lang-css.js
pug/docs/slidedeck-pdxpy/js/prettify/lang-go.js
pug/docs/slidedeck-pdxpy/js/prettify/lang-hs.js
pug/docs/slidedeck-pdxpy/js/prettify/lang-lisp.js
pug/docs/slidedeck-pdxpy/js/prettify/lang-lua.js
pug/docs/slidedeck-pdxpy/js/prettify/lang-ml.js
pug/docs/slidedeck-pdxpy/js/prettify/lang-n.js
pug/docs/slidedeck-pdxpy/js/prettify/lang-proto.js
pug/docs/slidedeck-pdxpy/js/prettify/lang-scala.js
