Metadata-Version: 1.1
Name: pug
Version: 0.1.22
Summary: Meta package to install the PDX Python User Group utilities.
Home-page: UNKNOWN
Author: Hobson Lane
Author-email: admin@totalgood.com
License: MIT
Keywords: natural language processing,text processing,neural net,science,data science,math,machine-learning,statistics,database
Platform: 
Classifier: Programming Language :: Python
Classifier: Programming Language :: Python :: 2.7
Classifier: Development Status :: 2 - Pre-Alpha
Classifier: Environment :: Other Environment
Classifier: Environment :: Console
Classifier: Intended Audience :: Developers
Classifier: License :: OSI Approved :: MIT License
Classifier: Operating System :: OS Independent
Classifier: Topic :: Software Development :: Libraries :: Python Modules
Classifier: Topic :: Scientific/Engineering :: Artificial Intelligence
Classifier: Topic :: Scientific/Engineering :: Mathematics
Classifier: Topic :: Internet :: WWW/HTTP :: Indexing/Search
